itemdetectionfromname/__init__.py
itemdetectionfromname-0.0.4.dist-info/LICENCE.txt
itemdetectionfromname-0.0.4.dist-info/METADATA
itemdetectionfromname-0.0.4.dist-info/WHEEL
itemdetectionfromname-0.0.4.dist-info/top_level.txt
itemdetectionfromname-0.0.4.dist-info/RECORD
