Metadata-Version: 2.1
Name: itemdetectionfromname
Version: 0.0.4
Summary: Proteus Invoiceitemdecription File
Author: Proteus Technology PVT. LTD.
Author-email: <apps@baseinformation.com>
Keywords: python,first package
Classifier: Development Status :: 3 - Alpha
Classifier: Intended Audience :: Education
Classifier: Programming Language :: Python :: 2
Classifier: Programming Language :: Python :: 3
Classifier: Operating System :: MacOS :: MacOS X
Classifier: Operating System :: Microsoft :: Windows
License-File: LICENCE.txt
Requires-Dist: requests
Requires-Dist: flask
Requires-Dist: loggerutility
